Metadata-Version: 1.0
Name: pysc1
Version: 0.0.3
Summary: StarCraft I Learning Environment
Home-page: https://github.com/bboyseiok/pysc1
Author: bboyseiok
Author-email: bboyseiok@deepest.ai
License: BSP
Platform: UNKNOWN
